ssh_commands/Singleton.py
ssh_commands/__init__.py
ssh_commands/commands.py
ssh_commands/ssh-expand-password
ssh_commands/ssh-expand-password-sleep
ssh_commands/update_version.py
ssh_commands-1.7.7.data/scripts/ssh-expand-password
ssh_commands-1.7.7.data/scripts/ssh-expand-password-sleep
ssh_commands-1.7.7.dist-info/METADATA
ssh_commands-1.7.7.dist-info/WHEEL
ssh_commands-1.7.7.dist-info/top_level.txt
ssh_commands-1.7.7.dist-info/RECORD
