Metadata-Version: 2.1
Name: ssh-commands
Version: 1.7.7
Summary: SSH commands and gitlab helper
Home-page: https://gitlab.infomir.dev/backend/python-packages/commands-helper
Author: Donii Sergii
Author-email: s.donii@infomir.com
License: UNKNOWN
Platform: UNKNOWN
Classifier: Programming Language :: Python :: 3
Classifier: License :: OSI Approved :: MIT License
Classifier: Operating System :: OS Independent
Requires-Dist: pyyaml
Requires-Dist: cryptography
Requires-Dist: python-gitlab
